geopydata/__init__.py
geopydata/common.py
geopydata/geopydata.py
geopydata-0.0.1.dist-info/LICENSE
geopydata-0.0.1.dist-info/METADATA
geopydata-0.0.1.dist-info/WHEEL
geopydata-0.0.1.dist-info/entry_points.txt
geopydata-0.0.1.dist-info/top_level.txt
geopydata-0.0.1.dist-info/RECORD
